hplog/__init__.py
hplog/hplog.py
hplog-0.15.0.dist-info/METADATA
hplog-0.15.0.dist-info/WHEEL
hplog-0.15.0.dist-info/entry_points.txt
hplog-0.15.0.dist-info/RECORD
